pythonic_fp/homepage/__init__.py
pythonic_fp/homepage/compatible_versions.py
pythonic_fp/homepage/development.py
pythonic_fp/homepage/intro.py
pythonic_fp/homepage/overview.py
pythonic_fp/homepage/py.typed
pythonic_fp/homepage/top_level_releases.py
pythonic_fp-3.2.2.dist-info/licenses/LICENSE
pythonic_fp-3.2.2.dist-info/WHEEL
pythonic_fp-3.2.2.dist-info/METADATA
pythonic_fp-3.2.2.dist-info/RECORD
