Metadata-Version: 2.4
Name: pythonic-fp
Version: 3.2.2
Summary: Purpose pythonic-fp PyPI Project
Keywords: functional,pythonic
Author-email: "Geoffrey R. Scheller" <geoffrey@scheller.com>
Requires-Python: >=3.13
Classifier: Development Status :: 4 - Beta
Classifier: Intended Audience :: Developers
Classifier: License :: OSI Approved :: Apache Software License
Classifier: Operating System :: OS Independent
Classifier: Programming Language :: Python :: 3.13
Classifier: Typing :: Typed
License-File: LICENSE
Project-URL: Changelog, https://github.com/grscheller/pythonic-fp/blob/main/CHANGELOG.rst
Project-URL: Homepage, https://grscheller.github.io/pythonic-fp/homepage/build/html/
Project-URL: Source, https://github.com/grscheller/pythonic-fp
